thesisv3/__init__.py
thesisv3/analysis/__init__.py
thesisv3/building/__init__.py
thesisv3/preprocessing/__init__.py
thesisv3/tests/__init__.py
thesisv3/tests/test_tuners.py
thesisv3/utils/__init__.py
thesisv3/utils/helpers.py
thesisv3/validation/__init__.py
thesisv3/validation/tuners.py
thesisv3-0.0.2.dist-info/METADATA
thesisv3-0.0.2.dist-info/WHEEL
thesisv3-0.0.2.dist-info/top_level.txt
thesisv3-0.0.2.dist-info/RECORD
