Metadata-Version: 2.1
Name: thesisv3
Version: 0.0.2
Summary: prototype package for Bomediano And Friends Thesis
Author: 5i5ousplay
Requires-Dist: contourpy==1.3.1
Requires-Dist: cvxopt==1.3.2
Requires-Dist: cycler==0.12.1
Requires-Dist: Cython==3.0.11
Requires-Dist: fonttools==4.55.0
Requires-Dist: future==1.0.0
Requires-Dist: GraKeL==0.1.10
Requires-Dist: joblib==1.4.2
Requires-Dist: kiwisolver==1.4.7
Requires-Dist: matplotlib==3.9.2
Requires-Dist: networkx==3.4.2
Requires-Dist: numpy==1.26.4
Requires-Dist: packaging==24.2
Requires-Dist: pandas==2.2.3
Requires-Dist: pillow==11.0.0
Requires-Dist: pyparsing==3.2.0
Requires-Dist: python-dateutil==2.9.0.post0
Requires-Dist: pytz==2024.2
Requires-Dist: scikit-learn==1.5.2
Requires-Dist: scipy==1.14.1
Requires-Dist: six==1.16.0
Requires-Dist: threadpoolctl==3.5.0
Requires-Dist: tzdata==2024.2
